LICENSE
README.md
setup.cfg
setup.py
DataQualityFramework.egg-info/PKG-INFO
DataQualityFramework.egg-info/SOURCES.txt
DataQualityFramework.egg-info/dependency_links.txt
DataQualityFramework.egg-info/requires.txt
DataQualityFramework.egg-info/top_level.txt
data_quality_framework/__init__.py
data_quality_framework/core.py
data_quality_framework/connection/__init__.py
data_quality_framework/connection/api.py
data_quality_framework/connection/file.py
data_quality_framework/connection/google.py
data_quality_framework/connection/postgresql.py
data_quality_framework/export/rules.py
data_quality_framework/quality/__init__.py
data_quality_framework/quality/comformity.py
data_quality_framework/quality/completeness.py
data_quality_framework/quality/consistency.py
data_quality_framework/quality/metadata.py
data_quality_framework/quality/timeliness.py
data_quality_framework/quality/uniqueness.py