Metadata-Version: 2.1
Name: DataQualityFramework
Version: 0.0.7
Summary: Data Quality Framework for Ekosistem Data Jabar
Home-page: https://gitlab.com/jdsteam/core-data-platform/data-quality-framework
Author: JDS's Data Engineer
Author-email: jds.dataengineer@gmail.com
License: AGPLv3
Download-URL: https://pypi.org/project/DataQualityFramework/#files
Keywords: data quality framework,data,quality,framework,validation,jabar digital service,jds,data engineer
Platform: any
Requires-Python: >=3
License-File: LICENSE
